CHANGELOG.md
CONTRIBUTING.md
LICENSE
MANIFEST.in
README.md
meson.build
pyproject.toml
setup.cfg
setup.py
OMMBV/__init__.py
OMMBV/_core.py
OMMBV/heritage.py
OMMBV/satellite.py
OMMBV/trace.py
OMMBV/trans.py
OMMBV/utils.py
OMMBV/vector.py
OMMBV/version.txt
OMMBV.egg-info/PKG-INFO
OMMBV.egg-info/SOURCES.txt
OMMBV.egg-info/dependency_links.txt
OMMBV.egg-info/not-zip-safe
OMMBV.egg-info/requires.txt
OMMBV.egg-info/top_level.txt
ommbvfortran/_coords.f
ommbvfortran/igrf14.f
ommbvfortran/sources.f