Metadata-Version: 2.1
Name: OMMBV
Version: 1.1.0
Summary: Orthogonal geomagnetic vector basis and field-line mapping for multipole magnetic fields.
Home-page: https://github.com/CosmicStudioSoftware/OMMBV/
Author: Russell A. Stoneback
Author-email: contact@cosmicstudio.io
Maintainer-email: Russell Stoneback <contact@cosmicstudio.io>
License: BSD 3-Clause License
Keywords: vector-basis,geomagnetic-field,magnetic-fields,field-line-tracing,meridional,zonal,field-aligned,satellite,electric-field-mapping,ion-drift-mapping,multipole,electrodynamics,plasma
Classifier: Development Status :: 5 - Production/Stable
Classifier: Topic :: Scientific/Engineering :: Physics
Classifier: Intended Audience :: Science/Research
Classifier: License :: OSI Approved :: BSD License
Classifier: Natural Language :: English
Classifier: Programming Language :: Python :: 3
Classifier: Programming Language :: Python :: 3.9
Classifier: Programming Language :: Python :: 3.10
Classifier: Programming Language :: Python :: 3.11
Classifier: Programming Language :: Python :: 3.12
Classifier: Operating System :: POSIX :: Linux
Classifier: Operating System :: POSIX
Classifier: Operating System :: MacOS
Requires-Python: >=3.9
License-File: LICENSE
